LICENSE.txt
README.md
setup.cfg
setup.py
scopeton/__init__.py
scopeton/annotation_tools.py
scopeton/compat.py
scopeton/constants.py
scopeton/decorators.py
scopeton/glob.py
scopeton/objects.py
scopeton/qualifier_tree.py
scopeton/scope.py
scopeton/scope_tools.py
scopeton/type_utils.py
scopeton.egg-info/PKG-INFO
scopeton.egg-info/SOURCES.txt
scopeton.egg-info/dependency_links.txt
scopeton.egg-info/requires.txt
scopeton.egg-info/top_level.txt
tests/test_annotation_tools.py